Workbook

Sheet Cover
B3: SPOTIFY TECHNOLOGY S.A.
B5: Driver-Based Revenue Forecast Model | FY2021A – FY2027E
B6: Driver-Based Revenue Forecast Model | FY2021A – FY2027E
B12: Prepared by: | C12: Alex Strong — Economist & Quantitative Analyst
B14: Data Sources: | C14: Spotify Investor Relations (Annual Reports, Shareholder Letters)
B16: Model Purpose: | C16: Bottom-up driver forecast of Premium & Ad-Supported revenue
B18: Scenarios: | C18: Base / Bull / Bear — toggle on Assumptions sheet
B20: Last Updated: | C20: May 2026
B24: Model Navigation
B26: Assumptions | C26: Key drivers: MAU growth, conversion, ARPU, ad load — edit blue cells
B27: Income Statement | C27: Revenue build + P&L summary linking to Assumptions
B28: Scenario Analysis | C28: Side-by-side Bear / Base / Bull outputs with sensitivity tables
B29: Charts | C29: Visual dashboard: revenue mix, MAU growth, ARPU trends
B30: Raw Data | C30: Historical actuals sourced from Spotify annual reports
B36: Disclaimer: This model is an independent analytical exercise for portfolio demonstration purposes only. It is not investment advice. All forecasts are the author's own estimates based on publicly available data.

Sheet Raw Data
A1: Spotify — Historical Actuals
A3: Metric | B3: Unit | C3: Source | D3: 2021A | E3: 2022A | F3: 2023A | G3: 2024A
A5: Monthly Active Users (MAU) | B5: MM users | C5: Spotify Q4 Shareholder Letter, respective years | D5: 406 | E5: 456 | F5: 602 | G5: 678
A6: Premium Subscribers | B6: MM users | C6: Spotify Q4 Shareholder Letter, respective years | D6: 180 | E6: 205 | F6: 236 | G6: 263
A7: Premium Conversion Rate (Sub/MAU) | B7: % | C7: Calculated: Premium Subs / MAU | D7: =D6/D5 -> 0.44334975 | E7: =E6/E5 -> 0.4495614 | F7: =F6/F5 -> 0.39202658 | G7: =G6/G5 -> 0.3879056
A8: Premium ARPU (monthly) | B8: EUR | C8: Spotify Q4 Shareholder Letter, respective years | D8: 4.42 | E8: 4.35 | F8: 4.27 | G8: 4.5
A9: Premium Revenue | B9: EUR MM | C9: Spotify Annual Report, respective years | D9: 7135 | E9: 8463 | F9: 11566 | G9: 13573
A10: Ad-Supported MAU | B10: MM users | C10: Calculated: Total MAU - Premium Subs | D10: =D5-D6 -> 226 | E10: =E5-E6 -> 251 | F10: =F5-F6 -> 366 | G10: =G5-G6 -> 415
A11: Ad Revenue per MAU (annual) | B11: EUR | C11: Calculated: Ad Rev / Ad MAU | D11: =D12/D10 -> 5.3451327 | E11: =E12/E10 -> 5.8645418 | F11: =F12/F10 -> 4.5874317 | G11: =G12/G10 -> 4.6313253
A12: Ad-Supported Revenue | B12: EUR MM | C12: Spotify Annual Report, respective years | D12: 1208 | E12: 1472 | F12: 1679 | G12: 1922
A13: Total Revenue | B13: EUR MM | C13: Spotify Annual Report, respective years | D13: 9668 | E13: 11727 | F13: 13247 | G13: 15673
A14: Gross Profit | B14: EUR MM | C14: Spotify Annual Report, respective years | D14: 2336 | E14: 2699 | F14: 3038 | G14: 3781
A15: Gross Margin | B15: % | C15: Calculated | D15: =D14/D13 -> 0.24162185 | E15: =E14/E13 -> 0.23015264 | F15: =F14/F13 -> 0.22933494 | G15: =G14/G13 -> 0.2412429
A16: R&D Expense | B16: EUR MM | C16: Spotify Annual Report, respective years | D16: 1208 | E16: 1471 | F16: 1490 | G16: 1622
A17: S&M Expense | B17: EUR MM | C17: Spotify Annual Report, respective years | D17: 1093 | E17: 1291 | F17: 1158 | G17: 1116
A18: G&A Expense | B18: EUR MM | C18: Spotify Annual Report, respective years | D18: 396 | E18: 577 | F18: 576 | G18: 546
A19: Operating Income (Loss) | B19: EUR MM | C19: Spotify Annual Report, respective years | D19: -34 | E19: -659 | F19: -302 | G19: 1361
A20: Operating Margin | B20: % | C20: Calculated | D20: =D19/D13 -> -0.0035167563 | E20: =E19/E13 -> -0.056195105 | F20: =F19/F13 -> -0.022797615 | G20: =G19/G13 -> 0.086837236

Sheet Assumptions
A1: Assumptions — Edit Blue Cells
A2: Blue cells = inputs you can change. Switch scenario in B4 to auto-populate. Override individual cells by typing directly.
A4: Active Scenario | B4: Base | C4: ← Type: Base | Bull | Bear
A6: Driver | B6: Unit | C6: 2025E | D6: 2026E | E6: 2027E
A8: MAU & SUBSCRIBER GROWTH
A9: MAU YoY Growth Rate | B9: % | C9: =IF($B$4="Bull",0.14,IF($B$4="Bear",0.08,0.115)) -> 0.115 | D9: =IF($B$4="Bull",0.13,IF($B$4="Bear",0.07,0.105)) -> 0.105 | E9: =IF($B$4="Bull",0.12,IF($B$4="Bear",0.06,0.095)) -> 0.095
A10: Premium Conversion Rate | B10: % | C10: =IF($B$4="Bull",0.405,IF($B$4="Bear",0.375,0.392)) -> 0.392 | D10: =IF($B$4="Bull",0.415,IF($B$4="Bear",0.37,0.395)) -> 0.395 | E10: =IF($B$4="Bull",0.425,IF($B$4="Bear",0.365,0.4)) -> 0.4
A12: PREMIUM REVENUE DRIVERS
A13: Premium Monthly ARPU (EUR) | B13: EUR | C13: =IF($B$4="Bull",4.65,IF($B$4="Bear",4.4,4.55)) -> 4.55 | D13: =IF($B$4="Bull",4.8,IF($B$4="Bear",4.35,4.62)) -> 4.62 | E13: =IF($B$4="Bull",4.95,IF($B$4="Bear",4.3,4.7)) -> 4.7
A14: Premium ARPU YoY Growth | B14: % | C14: See ARPU row | D14: See ARPU row | E14: See ARPU row
A16: AD-SUPPORTED REVENUE DRIVERS
A17: Ad Revenue per Ad MAU (EUR/yr) | B17: EUR | C17: =IF($B$4="Bull",3.5,IF($B$4="Bear",2.9,3.2)) -> 3.2 | D17: =IF($B$4="Bull",3.75,IF($B$4="Bear",2.95,3.35)) -> 3.35 | E17: =IF($B$4="Bull",4,IF($B$4="Bear",3,3.5)) -> 3.5
A18: Ad Load Growth YoY | B18: % | C18: =IF($B$4="Bull",0.08,IF($B$4="Bear",0.03,0.05)) -> 0.05 | D18: =IF($B$4="Bull",0.09,IF($B$4="Bear",0.03,0.06)) -> 0.06 | E18: =IF($B$4="Bull",0.1,IF($B$4="Bear",0.04,0.07)) -> 0.07
A20: MARGIN ASSUMPTIONS
A21: Gross Margin | B21: % | C21: =IF($B$4="Bull",0.31,IF($B$4="Bear",0.265,0.285)) -> 0.285 | D21: =IF($B$4="Bull",0.33,IF($B$4="Bear",0.27,0.3)) -> 0.3 | E21: =IF($B$4="Bull",0.35,IF($B$4="Bear",0.275,0.315)) -> 0.315
A22: R&D as % of Revenue | B22: % | C22: =IF($B$4="Bull",0.1,IF($B$4="Bear",0.12,0.11)) -> 0.11 | D22: =IF($B$4="Bull",0.095,IF($B$4="Bear",0.118,0.105)) -> 0.105 | E22: =IF($B$4="Bull",0.09,IF($B$4="Bear",0.115,0.1)) -> 0.1
A23: S&M as % of Revenue | B23: % | C23: =IF($B$4="Bull",0.065,IF($B$4="Bear",0.085,0.075)) -> 0.075 | D23: =IF($B$4="Bull",0.06,IF($B$4="Bear",0.082,0.07)) -> 0.07 | E23: =IF($B$4="Bull",0.055,IF($B$4="Bear",0.08,0.065)) -> 0.065
A24: G&A as % of Revenue | B24: % | C24: =IF($B$4="Bull",0.033,IF($B$4="Bear",0.042,0.038)) -> 0.038 | D24: =IF($B$4="Bull",0.03,IF($B$4="Bear",0.04,0.035)) -> 0.035 | E24: =IF($B$4="Bull",0.028,IF($B$4="Bear",0.038,0.033)) -> 0.033

Sheet Income Statement
A1: Spotify — Revenue Build & P&L Summary (EUR Millions)
A3: Line Item | B3: 2021A | C3: 2022A | D3: 2023A | E3: 2024A | F3: 2025E | G3: 2026E | H3: 2027E
A5: USER METRICS
A6: Monthly Active Users (MM) | B6: ='Raw Data'!D5 -> 406 | C6: ='Raw Data'!E5 -> 456 | D6: ='Raw Data'!F5 -> 602 | E6: ='Raw Data'!G5 -> 678 | F6: =E6*(1+Assumptions!C9) -> 755.97 | G6: =F6*(1+Assumptions!D9) -> 835.34685 | H6: =G6*(1+Assumptions!E9) -> 914.7048
A7: Premium Subscribers (MM) | B7: ='Raw Data'!D6 -> 180 | C7: ='Raw Data'!E6 -> 205 | D7: ='Raw Data'!F6 -> 236 | E7: ='Raw Data'!G6 -> 263 | F7: =E6*Assumptions!C10 -> 265.776 | G7: =F6*Assumptions!D10 -> 298.60815 | H7: =G6*Assumptions!E10 -> 334.13874
A8: Premium Conversion Rate | B8: =B7/B6 -> 0.44334975 | C8: =C7/C6 -> 0.4495614 | D8: =D7/D6 -> 0.39202658 | E8: =E7/E6 -> 0.3879056 | F8: =F7/F6 -> 0.35156951 | G8: =G7/G6 -> 0.35746606 | H8: =H7/H6 -> 0.3652968
A9: Ad-Supported MAU (MM) | B9: =B6-B7 -> 226 | C9: =C6-C7 -> 251 | D9: =D6-D7 -> 366 | E9: =E6-E7 -> 415 | F9: =F6-F7 -> 490.194 | G9: =G6-G7 -> 536.7387 | H9: =H6-H7 -> 580.56606
A11: PREMIUM REVENUE BUILD
A12: Monthly ARPU (EUR) | B12: ='Raw Data'!D8 -> 4.42 | C12: ='Raw Data'!E8 -> 4.35 | D12: ='Raw Data'!F8 -> 4.27 | E12: ='Raw Data'!G8 -> 4.5 | F12: =Assumptions!C13 -> 4.55 | G12: =Assumptions!D13 -> 4.62 | H12: =Assumptions!E13 -> 4.7
A13: Premium Revenue (EUR MM) | B13: ='Raw Data'!D9 -> 7135 | C13: ='Raw Data'!E9 -> 8463 | D13: ='Raw Data'!F9 -> 11566 | E13: ='Raw Data'!G9 -> 13573 | F13: =F7*F12*12 -> 14511.37 | G13: =G7*G12*12 -> 16554.836 | H13: =H7*H12*12 -> 18845.425
A15: AD-SUPPORTED REVENUE BUILD
A16: Ad Revenue per Ad MAU (EUR/yr) | B16: ='Raw Data'!D11 -> 5.3451327 | C16: ='Raw Data'!E11 -> 5.8645418 | D16: ='Raw Data'!F11 -> 4.5874317 | E16: ='Raw Data'!G11 -> 4.6313253 | F16: =Assumptions!C17 -> 3.2 | G16: =Assumptions!D17 -> 3.35 | H16: =Assumptions!E17 -> 3.5
A17: Ad-Supported Revenue (EUR MM) | B17: ='Raw Data'!D12 -> 1208 | C17: ='Raw Data'!E12 -> 1472 | D17: ='Raw Data'!F12 -> 1679 | E17: ='Raw Data'!G12 -> 1922 | F17: =F9*F16 -> 1568.6208 | G17: =G9*G16 -> 1798.0746 | H17: =H9*H16 -> 2031.9812
A19: TOTAL REVENUE & P&L SUMMARY
A20: Total Revenue (EUR MM) | B20: =B13+B17 -> 8343 | C20: =C13+C17 -> 9935 | D20: =D13+D17 -> 13245 | E20: =E13+E17 -> 15495 | F20: =F13+F17 -> 16079.99 | G20: =G13+G17 -> 18352.91 | H20: =H13+H17 -> 20877.406
A21: YoY Revenue Growth | B21: - | C21: =(C20-B20)/B20 -> 0.19081865 | D21: =(D20-C20)/C20 -> 0.33316558 | E21: =(E20-D20)/D20 -> 0.16987542 | F21: =(F20-E20)/E20 -> 0.037753495 | G21: =(G20-F20)/F20 -> 0.14135084 | H21: =(H20-G20)/G20 -> 0.13755288
A22: Premium Revenue Mix | B22: =B13/B20 -> 0.85520796 | C22: =C13/C20 -> 0.85183694 | D22: =D13/D20 -> 0.87323518 | E22: =E13/E20 -> 0.87595999 | F22: =F13/F20 -> 0.9024489 | G22: =G13/G20 -> 0.90202782 | H22: =H13/H20 -> 0.9026708
A23: Ad-Supported Revenue Mix | B23: =B17/B20 -> 0.14479204 | C23: =C17/C20 -> 0.14816306 | D23: =D17/D20 -> 0.12676482 | E23: =E17/E20 -> 0.12404001 | F23: =F17/F20 -> 0.097551103 | G23: =G17/G20 -> 0.09797218 | H23: =H17/H20 -> 0.097329199
A25: Gross Profit (EUR MM) | B25: ='Raw Data'!D14 -> 2336 | C25: ='Raw Data'!E14 -> 2699 | D25: ='Raw Data'!F14 -> 3038 | E25: ='Raw Data'!G14 -> 3781 | F25: =F20*Assumptions!C21 -> 4582.7973 | G25: =G20*Assumptions!D21 -> 5505.8731 | H25: =H20*Assumptions!E21 -> 6576.3829
A26: Gross Margin | B26: =B25/B20 -> 0.27999521 | C26: =C25/C20 -> 0.27166583 | D26: =D25/D20 -> 0.22936957 | E26: =E25/E20 -> 0.2440142 | F26: =F25/F20 -> 0.285 | G26: =G25/G20 -> 0.3 | H26: =H25/H20 -> 0.315
A27: R&D Expense (EUR MM) | B27: ='Raw Data'!D16 -> 1208 | C27: ='Raw Data'!E16 -> 1471 | D27: ='Raw Data'!F16 -> 1490 | E27: ='Raw Data'!G16 -> 1622 | F27: =-F20*Assumptions!C22 -> -1768.7989 | G27: =-G20*Assumptions!D22 -> -1927.0556 | H27: =-H20*Assumptions!E22 -> -2087.7406
A28: S&M Expense (EUR MM) | B28: ='Raw Data'!D17 -> 1093 | C28: ='Raw Data'!E17 -> 1291 | D28: ='Raw Data'!F17 -> 1158 | E28: ='Raw Data'!G17 -> 1116 | F28: =-F20*Assumptions!C23 -> -1205.9993 | G28: =-G20*Assumptions!D23 -> -1284.7037 | H28: =-H20*Assumptions!E23 -> -1357.0314
A29: G&A Expense (EUR MM) | B29: ='Raw Data'!D18 -> 396 | C29: ='Raw Data'!E18 -> 577 | D29: ='Raw Data'!F18 -> 576 | E29: ='Raw Data'!G18 -> 546 | F29: =-F20*Assumptions!C24 -> -611.03964 | G29: =-G20*Assumptions!D24 -> -642.35187 | H29: =-H20*Assumptions!E24 -> -688.9544
A30: Operating Income (EUR MM) | B30: =B25+B27+B28+B29 -> 5033 | C30: =C25+C27+C28+C29 -> 6038 | D30: =D25+D27+D28+D29 -> 6262 | E30: =E25+E27+E28+E29 -> 7065 | F30: =F25+F27+F28+F29 -> 996.9594 | G30: =G25+G27+G28+G29 -> 1651.7619 | H30: =H25+H27+H28+H29 -> 2442.6565
A31: Operating Margin | B31: =B30/B20 -> 0.60326022 | C31: =C30/C20 -> 0.60775038 | D31: =D30/D20 -> 0.47278218 | E31: =E30/E20 -> 0.45595353 | F31: =F30/F20 -> 0.062 | G31: =G30/G20 -> 0.09 | H31: =H30/H20 -> 0.117

Sheet Scenario Analysis
A1: Scenario Analysis — Bear / Base / Bull
A2: This sheet hard-codes each scenario's key outputs for side-by-side comparison. Change the active scenario on the Assumptions sheet to update the Income Statement live.
A4: Metric | B4: Bear 2025E | C4: Bear 2026E | D4: Bear 2027E | E4: Base 2025E | F4: Base 2026E | G4: Base 2027E | H4: Bull 2025E | I4: Bull 2026E | J4: Bull 2027E
A6: MAU (MM) | B6: 732 | C6: 783 | D6: 830 | E6: 756 | F6: 834 | G6: 913 | H6: 771 | I6: 871 | J6: 976
A7: Premium Subscribers (MM) | B7: 275 | C7: 290 | D7: 303 | E7: 297 | F7: 330 | G7: 365 | H7: 312 | I7: 362 | J7: 415
A8: Premium Revenue (EUR MM) | B8: 14540 | C8: 15225 | D8: 15665 | E8: 16215 | F8: 18330 | G8: 20625 | H8: 17432 | I8: 20884 | J8: 25047
A9: Ad-Supported Revenue (MM) | B9: 1335 | C9: 1389 | D9: 1422 | E9: 1468 | F9: 1609 | G9: 1802 | H9: 1617 | I9: 1890 | J9: 2254
A10: Total Revenue (EUR MM) | B10: 15875 | C10: 16614 | D10: 17087 | E10: 17683 | F10: 19939 | G10: 22427 | H10: 19049 | I10: 22774 | J10: 27301
A11: Gross Margin | B11: 0.265 | C11: 0.27 | D11: 0.275 | E11: 0.285 | F11: 0.3 | G11: 0.315 | H11: 0.31 | I11: 0.33 | J11: 0.35
A12: Operating Income (EUR MM) | B12: -420 | C12: -330 | D12: -210 | E12: 890 | F12: 1492 | G12: 2243 | H12: 1904 | I12: 3128 | J12: 5460
A13: Operating Margin | B13: -0.026 | C13: -0.02 | D13: -0.012 | E13: 0.05 | F13: 0.075 | G13: 0.1 | H13: 0.1 | I13: 0.137 | J13: 0.2
A14: Revenue YoY Growth | B14: 0.012 | C14: 0.047 | D14: 0.029 | E14: 0.128 | F14: 0.128 | G14: 0.125 | H14: 0.215 | I14: 0.195 | J14: 0.199
A20: SENSITIVITY TABLE — 2027E Operating Income (EUR MM)
A21: Rows = 2027E Gross Margin Assumption | Columns = 2027E MAU Growth Rate
A22: GM \ MAU Growth → | B22: 0.06 | C22: 0.08 | D22: 0.1 | E22: 0.12 | F22: 0.14 | G22: 0.16
A23: 0.26 | B23: 1235 | C23: 1306 | D23: 1380 | E23: 1456 | F23: 1536 | G23: 1618
A24: 0.275 | B24: 1533 | C24: 1622 | D24: 1714 | E24: 1809 | F24: 1907 | G24: 2009
A25: 0.29 | B25: 1832 | C25: 1938 | D25: 2047 | E25: 2161 | F25: 2279 | G25: 2401
A26: 0.305 | B26: 2131 | C26: 2254 | D26: 2381 | E26: 2513 | F26: 2650 | G26: 2792
A27: 0.32 | B27: 2429 | C27: 2570 | D27: 2715 | E27: 2866 | F27: 3022 | G27: 3184
A28: 0.335 | B28: 2728 | C28: 2885 | D28: 3049 | E28: 3218 | F28: 3394 | G28: 3575

Sheet Charts
A1: Spotify — Visual Dashboard Data
A2: Charts below pull from the Income Statement. Switch scenarios on the Assumptions sheet to see them update.
A4: Year | B4: Premium Revenue | C4: Ad Revenue | D4: Total Revenue
A5: 2021A | B5: ='Income Statement'!B13 -> 7135 | C5: ='Income Statement'!B17 -> 1208 | D5: ='Income Statement'!B20 -> 8343
A6: 2022A | B6: ='Income Statement'!C13 -> 8463 | C6: ='Income Statement'!C17 -> 1472 | D6: ='Income Statement'!C20 -> 9935
A7: 2023A | B7: ='Income Statement'!D13 -> 11566 | C7: ='Income Statement'!D17 -> 1679 | D7: ='Income Statement'!D20 -> 13245
A8: 2024A | B8: ='Income Statement'!E13 -> 13573 | C8: ='Income Statement'!E17 -> 1922 | D8: ='Income Statement'!E20 -> 15495
A9: 2025E | B9: ='Income Statement'!F13 -> 14511.37 | C9: ='Income Statement'!F17 -> 1568.6208 | D9: ='Income Statement'!F20 -> 16079.99
A10: 2026E | B10: ='Income Statement'!G13 -> 16554.836 | C10: ='Income Statement'!G17 -> 1798.0746 | D10: ='Income Statement'!G20 -> 18352.91
A11: 2027E | B11: ='Income Statement'!H13 -> 18845.425 | C11: ='Income Statement'!H17 -> 2031.9812 | D11: ='Income Statement'!H20 -> 20877.406
A15: Year | B15: Total MAU (MM) | C15: Premium Subs (MM) | D15: Conversion Rate
A16: 2021A | B16: ='Income Statement'!B6 -> 406 | C16: ='Income Statement'!B7 -> 180 | D16: ='Income Statement'!B7/'Income Statement'!B6 -> 0.44334975
A17: 2022A | B17: ='Income Statement'!C6 -> 456 | C17: ='Income Statement'!C7 -> 205 | D17: ='Income Statement'!C7/'Income Statement'!C6 -> 0.4495614
A18: 2023A | B18: ='Income Statement'!D6 -> 602 | C18: ='Income Statement'!D7 -> 236 | D18: ='Income Statement'!D7/'Income Statement'!D6 -> 0.39202658
A19: 2024A | B19: ='Income Statement'!E6 -> 678 | C19: ='Income Statement'!E7 -> 263 | D19: ='Income Statement'!E7/'Income Statement'!E6 -> 0.3879056
A20: 2025E | B20: ='Income Statement'!F6 -> 755.97 | C20: ='Income Statement'!F7 -> 265.776 | D20: ='Income Statement'!F7/'Income Statement'!F6 -> 0.35156951
A21: 2026E | B21: ='Income Statement'!G6 -> 835.34685 | C21: ='Income Statement'!G7 -> 298.60815 | D21: ='Income Statement'!G7/'Income Statement'!G6 -> 0.35746606
A22: 2027E | B22: ='Income Statement'!H6 -> 914.7048 | C22: ='Income Statement'!H7 -> 334.13874 | D22: ='Income Statement'!H7/'Income Statement'!H6 -> 0.3652968
